binod3/__init__.py
binod3/__main__.py
binod_binod-1.0.5.dist-info/LICENSE
binod_binod-1.0.5.dist-info/METADATA
binod_binod-1.0.5.dist-info/WHEEL
binod_binod-1.0.5.dist-info/entry_points.txt
binod_binod-1.0.5.dist-info/top_level.txt
binod_binod-1.0.5.dist-info/RECORD
